dewdrop/__init__.py
dewdrop/__main__.py
dewdrop/dewdrop.py
dewdrop-0.3.0.dist-info/licenses/LICENSE
dewdrop-0.3.0.dist-info/METADATA
dewdrop-0.3.0.dist-info/WHEEL
dewdrop-0.3.0.dist-info/entry_points.txt
dewdrop-0.3.0.dist-info/top_level.txt
dewdrop-0.3.0.dist-info/RECORD
