Metadata-Version: 2.4
Name: dewdrop
Version: 0.3.0
Summary: Interact with Dewey Data API from the command line.
Author-email: Chris Poliquin <chrispoliquin@gmail.com>
Project-URL: homepage, https://github.com/poliquin/dewdrop
Project-URL: repository, https://github.com/poliquin/dewdrop
Project-URL: issues, https://github.com/poliquin/dewdrop/issues
Keywords: Dewey,Dewey Data,API,data,academic,research
Classifier: Programming Language :: Python :: 3
Classifier: License :: OSI Approved :: MIT License
Classifier: Operating System :: OS Independent
Classifier: Topic :: Utilities
License-File: LICENSE
Requires-Dist: requests<3.0.0,>=2.32.0
Dynamic: license-file
